{"name": "生益电子股份有限公司", "ename": "Shengyi Electronics CO.,LTD.", "market": "上海证券交易所", "ldate": "2021-02-25", "sprice": "12.42", "principal": "东莞证券股份有限公司", "rdate": "1985-08-02", "rprice": "83182.1万元(CNY)", "instype": "其它", "organ": "--", "secre": "林江", "phone": "0769-89281988", "sphone": "0769-89281988", "fax": "0769-89281998", "sfax": "0769-89281998", "email": "bo@sye.com.cn", "semail": "bo@sye.com.cn", "site": "http://www.sye.com.cn", "post": "523127", "infosite": "--", "oname": "--", "addr": "广东省东莞市东城区(同沙)科技工业园同振路33号", "oaddr": "广东省东莞市东城区(同沙)科技工业园同振路33号", "desc": "1985年8月2日,公司前身“东莞生益电子有限公司”成立。     2016年6月20日,公司名称由“东莞生益电子有限公司”变更为“生益电子股份有限公司”。", "bscope": "各类印制电路板的研发、生产与销售业务。", "idea": "所属概念板块,大盘,融资融券,5G,苹果三星,MSCI中国,高派息,工业互联网,华为概念,PCB概念,光通信,汽车电子,MLED,CPO概念,毫米波雷达,交换机,百元股,年度强势", "printype": "--", "referrer": "--", "putype": "--", "pe": "--", "firgu": "--", "lastgu": "--", "realgu": "--", "planm": "--", "realm": "--", "pubfee": "--", "collect": "--", "signfee": "--", "pdate": "--"}